gcmprocpy/__init__.py
gcmprocpy/convert_units.py
gcmprocpy/data_emissions.py
gcmprocpy/data_parse.py
gcmprocpy/getoptions.py
gcmprocpy/io.py
gcmprocpy/main.py
gcmprocpy/mov_gen.py
gcmprocpy/plot_gen.py
gcmprocpy/cmd/__init__.py
gcmprocpy/cmd/cmd_lat_lon.py
gcmprocpy/cmd/cmd_lat_time.py
gcmprocpy/cmd/cmd_lev_lat.py
gcmprocpy/cmd/cmd_lev_lon.py
gcmprocpy/cmd/cmd_lev_time.py
gcmprocpy/cmd/cmd_lev_var.py
gcmprocpy/gui/__init__.py
gcmprocpy/gui/gcmprocpy.py
gcmprocpy/gui/gui_lev_var copy.py
gcmprocpy/gui/gui_lev_var_new.py
gcmprocpy/gui/gui_lev_var_old.py
gcmprocpy-1.2.1.dist-info/METADATA
gcmprocpy-1.2.1.dist-info/WHEEL
gcmprocpy-1.2.1.dist-info/entry_points.txt
gcmprocpy-1.2.1.dist-info/top_level.txt
gcmprocpy-1.2.1.dist-info/RECORD
