Metadata-Version: 2.1
Name: gcmprocpy
Version: 1.2.1
Summary: A Python3 post processing tool for TIE-GCM and WACCM-X
Home-page: https://github.com/NCAR/gcmprocpy
Author: Nikhil Rao
Author-email: nikhilr@ucar.edu
Requires-Python: >=3.8
Requires-Dist: cartopy
Requires-Dist: matplotlib
Requires-Dist: numpy
Requires-Dist: xarray
Requires-Dist: ipython
Requires-Dist: geomag
Requires-Dist: netcdf4
Requires-Dist: ipympl
Requires-Dist: mplcursors
Requires-Dist: PyQt5
